cloud_storage/__about__.py
cloud_storage/__init__.py
cloud_storage/enums.py
cloud_storage/excepts.py
cloud_storage/gcs_storage.py
cloud_storage/local_storage.py
cloud_storage/s3_storage_boto3.py
cloud_storage-1.6.0.dist-info/LICENSE
cloud_storage-1.6.0.dist-info/METADATA
cloud_storage-1.6.0.dist-info/WHEEL
cloud_storage-1.6.0.dist-info/top_level.txt
cloud_storage-1.6.0.dist-info/RECORD
