Metadata-Version: 2.1
Name: cloud-storage
Version: 1.6.0
Summary: Interface of S3 and Google Storgae
Home-page: https://github.com/Gatsby-Lee/cloud-storage
Author: Henley Kuang, Gatsby Lee
License: GPL-3.0
Keywords: cloud storage gcs s3
Platform: UNKNOWN
Classifier: Development Status :: 5 - Production/Stable
Classifier: Intended Audience :: Developers
Classifier: License :: OSI Approved :: GNU General Public License v3 (GPLv3)
Classifier: Programming Language :: Python
Classifier: Programming Language :: Python :: 3
Classifier: Programming Language :: Python :: 3.6
Classifier: Programming Language :: Python :: 3.7
Classifier: Topic :: Utilities
Requires-Python: >=3.6
Requires-Dist: boto3
Requires-Dist: google-cloud-storage (>=1.24.0)
Requires-Dist: six (>=1.15.0)
Provides-Extra: dev
Requires-Dist: pytest ; extra == 'dev'
Requires-Dist: pytest-mock ; extra == 'dev'
Requires-Dist: moto ; extra == 'dev'
Requires-Dist: wheel ; extra == 'dev'
Requires-Dist: bpython ; extra == 'dev'
Requires-Dist: pylint ; extra == 'dev'
Requires-Dist: black ; extra == 'dev'
Provides-Extra: test
Requires-Dist: pytest ; extra == 'test'
Requires-Dist: pytest-mock ; extra == 'test'
Requires-Dist: moto ; extra == 'test'
